CHANGELOG.txt
LICENSE.txt
MANIFEST.in
README.txt
setup.py
trucmap/__init__.py
trucmap/myfunctions.py
trucmap.egg-info/PKG-INFO
trucmap.egg-info/SOURCES.txt
trucmap.egg-info/dependency_links.txt
trucmap.egg-info/requires.txt
trucmap.egg-info/top_level.txt