Metadata-Version: 2.1
Name: trucmap
Version: 1.0.0
Summary: A color palette
Home-page: UNKNOWN
Author: Bhavithry Sen Puliparambil
Author-email: bhavithry@gmail.com
License: MIT
Keywords: tru
Platform: UNKNOWN
Classifier: Development Status :: 5 - Production/Stable
Classifier: Intended Audience :: Education
Classifier: Operating System :: Microsoft :: Windows :: Windows 10
Classifier: License :: OSI Approved :: MIT License
Classifier: Programming Language :: Python :: 3
License-File: LICENSE.txt
